[{"line":2,"elements":[{"start_timestamp":"2023-11-28T11:54:13.152Z","before":[{"result":{"duration":1000000,"status":"passed"},"match":{"location":"stepdefinitions.Hooks.setUpWeb()"}}],"line":4,"name":"Faire une assurance auto","description":"","id":"assurance-auto;faire-une-assurance-auto","type":"scenario","keyword":"Scenario","steps":[{"result":{"error_message":"org.openqa.selenium.SessionNotCreatedException: Could not start a new session. Possible causes are invalid address of the remote server or browser start-up failure. \nHost info: host: 'ZEPHYRUS', ip: '192.168.1.81'\r\n\tat org.openqa.selenium.remote.RemoteWebDriver.execute(RemoteWebDriver.java:536)\r\n\tat io.appium.java_client.AppiumDriver.startSession(AppiumDriver.java:274)\r\n\tat org.openqa.selenium.remote.RemoteWebDriver.<init>(RemoteWebDriver.java:159)\r\n\tat io.appium.java_client.AppiumDriver.<init>(AppiumDriver.java:89)\r\n\tat io.appium.java_client.AppiumDriver.<init>(AppiumDriver.java:101)\r\n\tat io.appium.java_client.android.AndroidDriver.<init>(AndroidDriver.java:113)\r\n\tat utils.DriverMobile.getDriver(DriverMobile.java:38)\r\n\tat pages.OrnikarWebPage.<init>(OrnikarWebPage.java:12)\r\n\tat stepdefinitions.OrnikarStepWeb.<init>(OrnikarStepWeb.java:13)\r\n\tat sun.reflect.NativeConstructorAccessorImpl.newInstance0(Native Method)\r\n\tat sun.reflect.NativeConstructorAccessorImpl.newInstance(NativeConstructorAccessorImpl.java:62)\r\n\tat sun.reflect.DelegatingConstructorAccessorImpl.newInstance(DelegatingConstructorAccessorImpl.java:45)\r\n\tat java.lang.reflect.Constructor.newInstance(Constructor.java:423)\r\n\tat org.picocontainer.injectors.AbstractInjector.newInstance(AbstractInjector.java:145)\r\n\tat org.picocontainer.injectors.ConstructorInjector$1.run(ConstructorInjector.java:342)\r\n\tat org.picocontainer.injectors.AbstractInjector$ThreadLocalCyclicDependencyGuard.observe(AbstractInjector.java:270)\r\n\tat org.picocontainer.injectors.ConstructorInjector.getComponentInstance(ConstructorInjector.java:364)\r\n\tat org.picocontainer.injectors.AbstractInjectionFactory$LifecycleAdapter.getComponentInstance(AbstractInjectionFactory.java:56)\r\n\tat org.picocontainer.behaviors.AbstractBehavior.getComponentInstance(AbstractBehavior.java:64)\r\n\tat org.picocontainer.behaviors.Stored.getComponentInstance(Stored.java:91)\r\n\tat org.picocontainer.DefaultPicoContainer.getInstance(DefaultPicoContainer.java:699)\r\n\tat org.picocontainer.DefaultPicoContainer.getComponent(DefaultPicoContainer.java:647)\r\n\tat org.picocontainer.DefaultPicoContainer.getComponent(DefaultPicoContainer.java:678)\r\n\tat io.cucumber.picocontainer.PicoFactory.getInstance(PicoFactory.java:54)\r\n\tat io.cucumber.java.AbstractGlueDefinition.invokeMethod(AbstractGlueDefinition.java:47)\r\n\tat io.cucumber.java.JavaStepDefinition.execute(JavaStepDefinition.java:29)\r\n\tat io.cucumber.core.runner.CoreStepDefinition.execute(CoreStepDefinition.java:66)\r\n\tat io.cucumber.core.runner.PickleStepDefinitionMatch.runStep(PickleStepDefinitionMatch.java:63)\r\n\tat io.cucumber.core.runner.ExecutionMode$1.execute(ExecutionMode.java:10)\r\n\tat io.cucumber.core.runner.TestStep.executeStep(TestStep.java:84)\r\n\tat io.cucumber.core.runner.TestStep.run(TestStep.java:56)\r\n\tat io.cucumber.core.runner.PickleStepTestStep.run(PickleStepTestStep.java:51)\r\n\tat io.cucumber.core.runner.TestCase.run(TestCase.java:84)\r\n\tat io.cucumber.core.runner.Runner.runPickle(Runner.java:75)\r\n\tat io.cucumber.junit.PickleRunners$NoStepDescriptions.lambda$run$0(PickleRunners.java:151)\r\n\tat io.cucumber.core.runtime.CucumberExecutionContext.lambda$runTestCase$5(CucumberExecutionContext.java:137)\r\n\tat io.cucumber.core.runtime.RethrowingThrowableCollector.executeAndThrow(RethrowingThrowableCollector.java:23)\r\n\tat io.cucumber.core.runtime.CucumberExecutionContext.runTestCase(CucumberExecutionContext.java:137)\r\n\tat io.cucumber.junit.PickleRunners$NoStepDescriptions.run(PickleRunners.java:148)\r\n\tat io.cucumber.junit.FeatureRunner.runChild(FeatureRunner.java:144)\r\n\tat io.cucumber.junit.FeatureRunner.runChild(FeatureRunner.java:28)\r\n\tat org.junit.runners.ParentRunner$4.run(ParentRunner.java:331)\r\n\tat org.junit.runners.ParentRunner$1.schedule(ParentRunner.java:79)\r\n\tat org.junit.runners.ParentRunner.runChildren(ParentRunner.java:329)\r\n\tat org.junit.runners.ParentRunner.access$100(ParentRunner.java:66)\r\n\tat org.junit.runners.ParentRunner$2.evaluate(ParentRunner.java:293)\r\n\tat org.junit.runners.ParentRunner$3.evaluate(ParentRunner.java:306)\r\n\tat org.junit.runners.ParentRunner.run(ParentRunner.java:413)\r\n\tat io.cucumber.junit.FeatureRunner.run(FeatureRunner.java:137)\r\n\tat io.cucumber.junit.Cucumber.runChild(Cucumber.java:196)\r\n\tat io.cucumber.junit.Cucumber.runChild(Cucumber.java:89)\r\n\tat org.junit.runners.ParentRunner$4.run(ParentRunner.java:331)\r\n\tat org.junit.runners.ParentRunner$1.schedule(ParentRunner.java:79)\r\n\tat org.junit.runners.ParentRunner.runChildren(ParentRunner.java:329)\r\n\tat org.junit.runners.ParentRunner.access$100(ParentRunner.java:66)\r\n\tat org.junit.runners.ParentRunner$2.evaluate(ParentRunner.java:293)\r\n\tat io.cucumber.core.runtime.CucumberExecutionContext.lambda$runFeatures$6(CucumberExecutionContext.java:148)\r\n\tat io.cucumber.core.runtime.CucumberExecutionContext.execute(CucumberExecutionContext.java:163)\r\n\tat io.cucumber.core.runtime.CucumberExecutionContext.runFeatures(CucumberExecutionContext.java:146)\r\n\tat io.cucumber.junit.Cucumber$StartAndFinishTestRun.evaluate(Cucumber.java:226)\r\n\tat org.junit.runners.ParentRunner$3.evaluate(ParentRunner.java:306)\r\n\tat org.junit.runners.ParentRunner.run(ParentRunner.java:413)\r\n\tat org.junit.runner.JUnitCore.run(JUnitCore.java:137)\r\n\tat com.intellij.junit4.JUnit4IdeaTestRunner.startRunnerWithArgs(JUnit4IdeaTestRunner.java:69)\r\n\tat com.intellij.rt.junit.IdeaTestRunner$Repeater$1.execute(IdeaTestRunner.java:38)\r\n\tat com.intellij.rt.execution.junit.TestsRepeater.repeat(TestsRepeater.java:11)\r\n\tat com.intellij.rt.junit.IdeaTestRunner$Repeater.startRunnerWithArgs(IdeaTestRunner.java:35)\r\n\tat com.intellij.rt.junit.JUnitStarter.prepareStreamsAndStart(JUnitStarter.java:232)\r\n\tat com.intellij.rt.junit.JUnitStarter.main(JUnitStarter.java:55)\r\nCaused by: org.openqa.selenium.WebDriverException: Connection refused: no further information\nBuild info: version: '4.11.0', revision: '040bc5406b'\nSystem info: os.name: 'Windows 11', os.arch: 'amd64', os.version: '10.0', java.version: '1.8.0_392'\nDriver info: driver.version: AndroidDriver\r\n\tat io.appium.java_client.remote.AppiumCommandExecutor.lambda$execute$4(AppiumCommandExecutor.java:262)\r\n\tat java.util.Optional.orElseGet(Optional.java:267)\r\n\tat io.appium.java_client.remote.AppiumCommandExecutor.execute(AppiumCommandExecutor.java:261)\r\n\tat org.openqa.selenium.remote.RemoteWebDriver.execute(RemoteWebDriver.java:518)\r\n\t... 68 more\r\nCaused by: java.net.ConnectException: Connection refused: no further information\r\n\tat sun.nio.ch.SocketChannelImpl.checkConnect(Native Method)\r\n\tat sun.nio.ch.SocketChannelImpl.finishConnect(SocketChannelImpl.java:716)\r\n\tat io.netty.channel.socket.nio.NioSocketChannel.doFinishConnect(NioSocketChannel.java:337)\r\n\tat io.netty.channel.nio.AbstractNioChannel$AbstractNioUnsafe.finishConnect(AbstractNioChannel.java:334)\r\n\tat io.netty.channel.nio.NioEventLoop.processSelectedKey(NioEventLoop.java:776)\r\n\tat io.netty.channel.nio.NioEventLoop.processSelectedKeysOptimized(NioEventLoop.java:724)\r\n\tat io.netty.channel.nio.NioEventLoop.processSelectedKeys(NioEventLoop.java:650)\r\n\tat io.netty.channel.nio.NioEventLoop.run(NioEventLoop.java:562)\r\n\tat io.netty.util.concurrent.SingleThreadEventExecutor$4.run(SingleThreadEventExecutor.java:997)\r\n\tat io.netty.util.internal.ThreadExecutorMap$2.run(ThreadExecutorMap.java:74)\r\n\tat io.netty.util.concurrent.FastThreadLocalRunnable.run(FastThreadLocalRunnable.java:30)\r\n\tat java.lang.Thread.run(Thread.java:750)\r\n","duration":3040000000,"status":"failed"},"line":5,"name":"l'utilisateur est connecté à Ornikar","match":{"location":"stepdefinitions.OrnikarStepWeb.lUtilisateurEstConnectéÀOrnikar()"},"keyword":"Given "},{"result":{"status":"skipped"},"line":6,"name":"l'utilisateur se trouve sur la page daccueil","match":{"location":"stepdefinitions.OrnikarStepWeb.lUtilisateurSeTrouveSurLaPageDaccueil()"},"keyword":"When "},{"result":{"status":"skipped"},"line":7,"name":"Cliquer sur Assurance Auto","match":{"location":"stepdefinitions.OrnikarStepWeb.cliquerSurAssuranceAuto()"},"keyword":"Then "}],"tags":[{"name":"@webOrnikar"}]}],"name":"Assurance Auto","description":"","id":"assurance-auto","keyword":"Feature","uri":"file:src/test/resources/features/OrnikarWeb.feature","tags":[{"name":"@webOrnikar","type":"Tag","location":{"line":1,"column":1}}]}]